{
  "templateKey": "pet-feeder",
  "displayName": "AI视觉智能宠物喂食器",
  "category": "生活黑科技",
  "keywords": "[\"pet feeder\",\"宠物喂食器\",\"智能喂食器\",\"automatic feeder\"]",
  "identificationResult": {
    "name": "AI视觉智能宠物喂食器",
    "category": "生活黑科技",
    "brief_description": "AI视觉智能宠物喂食器的详细拆解分析",
    "icon": "⌨️",
    "searchTerm": "pet feeder"
  },
  "treeData": {
    "root": {
      "name": "AI视觉智能宠物喂食器",
      "description": "一款集自动出粮、AI视觉识别、远程监控与互动于一体的智能宠物喂养设备。",
      "icon": "🐾",
      "searchTerm": "AI Vision Smart Pet Feeder",
      "children": [
        {
          "name": "机械与储粮系统",
          "description": "负责储存宠物干粮并精确控制出粮量的机械结构。",
          "is_raw_material": false,
          "icon": "⚙️",
          "searchTerm": "Mechanical Feeding System",
          "children": [
            {
              "name": "储粮桶",
              "description": "用于储存大量宠物干粮的密封容器。",
              "is_raw_material": false,
              "icon": "🪣",
              "searchTerm": "Food Hopper",
              "children": [
                {
                  "name": "塑料外壳",
                  "description": "构成储粮桶主体的塑料部件。",
                  "is_raw_material": false,
                  "icon": "🧱",
                  "searchTerm": "Plastic Housing",
                  "children": [
                    {
                      "name": "ABS塑料",
                      "description": "一种强度高、韧性好的工程塑料。",
                      "is_raw_material": false,
                      "icon": "🧪",
                      "searchTerm": "ABS Plastic",
                      "children": [
                        {
                          "name": "原油",
                          "description": "石油，是生产合成树脂的主要原料。",
                          "is_raw_material": true,
                          "icon": "🛢️",
                          "searchTerm": "Crude Oil",
                          "children": []
                        }
                      ]
                    }
                  ]
                },
                {
                  "name": "密封硅胶圈",
                  "description": "用于桶盖密封，防止粮食受潮。",
                  "is_raw_material": false,
                  "icon": "⭕",
                  "searchTerm": "Silicone Seal Ring",
                  "children": [
                    {
                      "name": "硅橡胶",
                      "description": "由硅胶制成的弹性密封材料。",
                      "is_raw_material": false,
                      "icon": "💧",
                      "searchTerm": "Silicone Rubber",
                      "children": [
                        {
                          "name": "硅砂",
                          "description": "二氧化硅，是生产硅元素的基础原料。",
                          "is_raw_material": true,
                          "icon": "🏖️",
                          "searchTerm": "Silica Sand",
                          "children": []
                        }
                      ]
                    }
                  ]
                }
              ]
            },
            {
              "name": "螺旋送料器",
              "description": "通过电机驱动螺旋杆旋转，定量推送粮食。",
              "is_raw_material": false,
              "icon": "🌀",
              "searchTerm": "Auger Feeder",
              "children": [
                {
                  "name": "直流电机",
                  "description": "提供旋转动力的微型电机。",
                  "is_raw_material": false,
                  "icon": "⚡",
                  "searchTerm": "DC Motor",
                  "children": [
                    {
                      "name": "永磁体",
                      "description": "电机中产生磁场的部件。",
                      "is_raw_material": false,
                      "icon": "🧲",
                      "searchTerm": "Permanent Magnet",
                      "children": [
                        {
                          "name": "钕铁硼",
                          "description": "一种高性能稀土永磁材料。",
                          "is_raw_material": false,
                          "icon": "⛏️",
                          "searchTerm": "Neodymium Magnet",
                          "children": [
                            {
                              "name": "稀土矿石",
                              "description": "如钕、镨等稀土元素的矿石。",
                              "is_raw_material": true,
                              "icon": "💎",
                              "searchTerm": "Rare Earth Ore",
                              "children": []
                            },
                            {
                              "name": "铁矿石",
                              "description": "用于提炼铁元素。",
                              "is_raw_material": true,
                              "icon": "🪨",
                              "searchTerm": "Iron Ore",
                              "children": []
                            }
                          ]
                        }
                      ]
                    },
                    {
                      "name": "漆包铜线",
                      "description": "用于绕制电机线圈。",
                      "is_raw_material": false,
                      "icon": "🔄",
                      "searchTerm": "Enameled Copper Wire",
                      "children": [
                        {
                          "name": "电解铜",
                          "description": "高纯度铜。",
                          "is_raw_material": false,
                          "icon": "🔶",
                          "searchTerm": "Electrolytic Copper",
                          "children": [
                            {
                              "name": "铜矿石",
                              "description": "如黄铜矿、斑铜矿等。",
                              "is_raw_material": true,
                              "icon": "🪨",
                              "searchTerm": "Copper Ore",
                              "children": []
                            }
                          ]
                        }
                      ]
                    }
                  ]
                },
                {
                  "name": "不锈钢螺旋杆",
                  "description": "直接接触并推送粮食的金属杆。",
                  "is_raw_material": false,
                  "icon": "🔩",
                  "searchTerm": "Stainless Steel Auger",
                  "children": [
                    {
                      "name": "不锈钢",
                      "description": "耐腐蚀的合金钢。",
                      "is_raw_material": false,
                      "icon": "🤘",
                      "searchTerm": "Stainless Steel",
                      "children": [
                        {
                          "name": "铁矿石",
                          "description": "用于炼铁。",
                          "is_raw_material": true,
                          "icon": "🪨",
                          "searchTerm": "Iron Ore",
                          "children": []
                        },
                        {
                          "name": "铬矿石",
                          "description": "如铬铁矿，提供耐腐蚀性。",
                          "is_raw_material": true,
                          "icon": "🪨",
                          "searchTerm": "Chromium Ore",
                          "children": []
                        }
                      ]
                    }
                  ]
                }
              ]
            }
          ]
        },
        {
          "name": "AI视觉与传感系统",
          "description": "包含摄像头、传感器和AI芯片，用于识别宠物、监控进食和互动。",
          "is_raw_material": false,
          "icon": "👁️",
          "searchTerm": "AI Vision and Sensor System",
          "children": [
            {
              "name": "摄像头模组",
              "description": "用于拍摄宠物视频和图像。",
              "is_raw_material": false,
              "icon": "📷",
              "searchTerm": "Camera Module",
              "children": [
                {
                  "name": "图像传感器",
                  "description": "将光学图像转换成电子信号的核心芯片。",
                  "is_raw_material": false,
                  "icon": "🔬",
                  "searchTerm": "Image Sensor (CMOS)",
                  "children": [
                    {
                      "name": "硅晶圆",
                      "description": "制造半导体芯片的基底材料。",
                      "is_raw_material": false,
                      "icon": "💿",
                      "searchTerm": "Silicon Wafer",
                      "children": [
                        {
                          "name": "高纯硅",
                          "description": "半导体级单晶硅。",
                          "is_raw_material": false,
                          "icon": "🔘",
                          "searchTerm": "High Purity Silicon",
                          "children": [
                            {
                              "name": "硅砂",
                              "description": "二氧化硅，提纯后得到多晶硅。",
                              "is_raw_material": true,
                              "icon": "🏖️",
                              "searchTerm": "Silica Sand",
                              "children": []
                            }
                          ]
                        }
                      ]
                    }
                  ]
                },
                {
                  "name": "光学镜头",
                  "description": "由多片透镜组成，用于聚焦光线。",
                  "is_raw_material": false,
                  "icon": "🔍",
                  "searchTerm": "Optical Lens",
                  "children": [
                    {
                      "name": "光学玻璃",
                      "description": "高透光率、低畸变的特种玻璃。",
                      "is_raw_material": false,
                      "icon": "🥃",
                      "searchTerm": "Optical Glass",
                      "children": [
                        {
                          "name": "硅砂",
                          "description": "玻璃的主要成分。",
                          "is_raw_material": true,
                          "icon": "🏖️",
                          "searchTerm": "Silica Sand",
                          "children": []
                        },
                        {
                          "name": "纯碱",
                          "description": "碳酸钠，降低玻璃熔点。",
                          "is_raw_material": false,
                          "icon": "🧂",
                          "searchTerm": "Soda Ash",
                          "children": []
                        }
                      ]
                    }
                  ]
                }
              ]
            },
            {
              "name": "AI处理芯片",
              "description": "用于运行视觉识别算法的专用处理器。",
              "is_raw_material": false,
              "icon": "🧠",
              "searchTerm": "AI Processing Chip",
              "children": [
                {
                  "name": "半导体晶圆",
                  "description": "集成了数十亿晶体管的硅芯片。",
                  "is_raw_material": false,
                  "icon": "💾",
                  "searchTerm": "Semiconductor Wafer",
                  "children": [
                    {
                      "name": "高纯硅",
                      "description": "半导体级单晶硅。",
                      "is_raw_material": false,
                      "icon": "🔘",
                      "searchTerm": "High Purity Silicon",
                      "children": [
                        {
                          "name": "硅砂",
                          "description": "二氧化硅，提纯后得到多晶硅。",
                          "is_raw_material": true,
                          "icon": "🏖️",
                          "searchTerm": "Silica Sand",
                          "children": []
                        }
                      ]
                    }
                  ]
                }
              ]
            }
          ]
        },
        {
          "name": "控制与供电系统",
          "description": "设备的主控电路、电源管理及网络连接模块。",
          "is_raw_material": false,
          "icon": "🔌",
          "searchTerm": "Control and Power System",
          "children": [
            {
              "name": "主控电路板 (PCB)",
              "description": "集成主控MCU、内存、电源管理等电路的基板。",
              "is_raw_material": false,
              "icon": "🟢",
              "searchTerm": "Main Control PCB",
              "children": [
                {
                  "name": "覆铜板",
                  "description": "PCB的基材，由绝缘层和铜箔构成。",
                  "is_raw_material": false,
                  "icon": "📜",
                  "searchTerm": "Copper Clad Laminate",
                  "children": [
                    {
                      "name": "玻璃纤维布",
                      "description": "增强材料，提供机械强度。",
                      "is_raw_material": false,
                      "icon": "🧵",
                      "searchTerm": "Fiberglass Cloth",
                      "children": [
                        {
                          "name": "硅砂",
                          "description": "熔融后拉丝制成玻璃纤维。",
                          "is_raw_material": true,
                          "icon": "🏖️",
                          "searchTerm": "Silica Sand",
                          "children": []
                        }
                      ]
                    },
                    {
                      "name": "环氧树脂",
                      "description": "粘合剂，将各层粘合并绝缘。",
                      "is_raw_material": false,
                      "icon": "🫙",
                      "searchTerm": "Epoxy Resin",
                      "children": [
                        {
                          "name": "原油",
                          "description": "提炼出苯、丙烯等化工原料。",
                          "is_raw_material": true,
                          "icon": "🛢️",
                          "searchTerm": "Crude Oil",
                          "children": []
                        }
                      ]
                    },
                    {
                      "name": "电解铜箔",
                      "description": "附着在基板上的导电层。",
                      "is_raw_material": false,
                      "icon": "🥮",
                      "searchTerm": "Electrolytic Copper Foil",
                      "children": [
                        {
                          "name": "电解铜",
                          "description": "高纯度铜。",
                          "is_raw_material": false,
                          "icon": "🔶",
                          "searchTerm": "Electrolytic Copper",
                          "children": [
                            {
                              "name": "铜矿石",
                              "description": "如黄铜矿、斑铜矿等。",
                              "is_raw_material": true,
                              "icon": "🪨",
                              "searchTerm": "Copper Ore",
                              "children": []
                            }
                          ]
                        }
                      ]
                    }
                  ]
                }
              ]
            },
            {
              "name": "锂离子电池",
              "description": "备用电源，防止断电时设备无法工作。",
              "is_raw_material": false,
              "icon": "🔋",
              "searchTerm": "Lithium-ion Battery",
              "children": [
                {
                  "name": "正极材料",
                  "description": "通常为钴酸锂或磷酸铁锂。",
                  "is_raw_material": false,
                  "icon": "➕",
                  "searchTerm": "Cathode Material",
                  "children": [
                    {
                      "name": "锂矿石",
                      "description": "如锂辉石、锂云母，提取锂元素。",
                      "is_raw_material": true,
                      "icon": "⛏️",
                      "searchTerm": "Lithium Ore",
                      "children": []
                    },
                    {
                      "name": "钴矿石",
                      "description": "用于生产钴酸锂。",
                      "is_raw_material": true,
                      "icon": "⛏️",
                      "searchTerm": "Cobalt Ore",
                      "children": []
                    }
                  ]
                },
                {
                  "name": "负极材料",
                  "description": "通常为人造石墨。",
                  "is_raw_material": false,
                  "icon": "➖",
                  "searchTerm": "Anode Material",
                  "children": [
                    {
                      "name": "石油焦",
                      "description": "生产石墨的原料之一。",
                      "is_raw_material": false,
                      "icon": "⚫",
                      "searchTerm": "Petroleum Coke",
                      "children": [
                        {
                          "name": "原油",
                          "description": "石油焦是原油精炼的副产品。",
                          "is_raw_material": true,
                          "icon": "🛢️",
                          "searchTerm": "Crude Oil",
                          "children": []
                        }
                      ]
                    }
                  ]
                }
              ]
            }
          ]
        },
        {
          "name": "外壳与结构件",
          "description": "设备的外部保护壳和内部支撑结构。",
          "is_raw_material": false,
          "icon": "🏠",
          "searchTerm": "Housing and Structural Parts",
          "children": [
            {
              "name": "主壳体",
              "description": "设备的外部主体结构。",
              "is_raw_material": false,
              "icon": "📦",
              "searchTerm": "Main Housing",
              "children": [
                {
                  "name": "ABS塑料",
                  "description": "一种强度高、韧性好的工程塑料。",
                  "is_raw_material": false,
                  "icon": "🧪",
                  "searchTerm": "ABS Plastic",
                  "children": [
                    {
                      "name": "原油",
                      "description": "石油，是生产合成树脂的主要原料。",
                      "is_raw_material": true,
                      "icon": "🛢️",
                      "searchTerm": "Crude Oil",
                      "children": []
                    }
                  ]
                }
              ]
            },
            {
              "name": "不锈钢食盆",
              "description": "宠物直接进食的容器，易于清洁。",
              "is_raw_material": false,
              "icon": "🥣",
              "searchTerm": "Stainless Steel Bowl",
              "children": [
                {
                  "name": "不锈钢板",
                  "description": "经冲压成型的不锈钢薄板。",
                  "is_raw_material": false,
                  "icon": "📏",
                  "searchTerm": "Stainless Steel Sheet",
                  "children": [
                    {
                      "name": "不锈钢",
                      "description": "耐腐蚀的合金钢。",
                      "is_raw_material": false,
                      "icon": "🤘",
                      "searchTerm": "Stainless Steel",
                      "children": [
                        {
                          "name": "铁矿石",
                          "description": "用于炼铁。",
                          "is_raw_material": true,
                          "icon": "🪨",
                          "searchTerm": "Iron Ore",
                          "children": []
                        },
                        {
                          "name": "铬矿石",
                          "description": "如铬铁矿，提供耐腐蚀性。",
                          "is_raw_material": true,
                          "icon": "🪨",
                          "searchTerm": "Chromium Ore",
                          "children": []
                        }
                      ]
                    }
                  ]
                }
              ]
            }
          ]
        }
      ]
    }
  },
  "nodePositions": {},
  "agentReports": {
    "market_analyst": {
      "analysis_report": {
        "product_name": "AI视觉智能宠物喂食器",
        "market_positioning": {
          "core_value_proposition": "通过AI视觉识别与智能算法，实现个性化、精准化、远程交互式的宠物喂养解决方案",
          "positioning_tier": "高端智能宠物用品",
          "key_differentiators": [
            "AI视觉识别宠物身份与状态",
            "智能食量控制与健康建议",
            "远程互动与监控功能",
            "多宠物识别与差异化喂养"
          ]
        },
        "target_users": {
          "primary_segments": [
            {
              "segment_name": "高收入都市年轻专业人士",
              "characteristics": "工作繁忙、注重科技体验、愿意为宠物健康投资、宠物视为家庭成员"
            },
            {
              "segment_name": "多宠物家庭",
              "characteristics": "需要管理不同宠物的差异化饮食需求、寻求喂养便利性"
            },
            {
              "segment_name": "关注宠物健康的精细化养宠人群",
              "characteristics": "关注宠物饮食数据、有科学养宠理念、接受智能硬件"
            }
          ],
          "user_scenarios": [
            "工作日远程喂养与互动",
            "宠物饮食健康数据追踪",
            "临时外出时的智能照护",
            "多宠物分食管理"
          ]
        },
        "competitive_landscape": {
          "direct_competitors": [
            {
              "type": "高端智能喂食器品牌",
              "examples": [
                "Petkit",
                "小佩"
              ],
              "competitive_analysis": "已具备基础智能功能，但AI视觉与深度交互能力较弱"
            }
          ],
          "indirect_competitors": [
            {
              "type": "传统自动喂食器",
              "competitive_analysis": "价格低廉但功能单一，缺乏智能化和交互性"
            },
            {
              "type": "宠物摄像头与喂食器组合方案",
              "competitive_analysis": "功能分离，体验不集成"
            }
          ],
          "competitive_advantage": "AI视觉技术带来的精准识别与交互能力，形成技术壁垒"
        },
        "market_trends": {
          "macro_trends": [
            {
              "trend": "宠物人性化与家庭化",
              "impact": "推动高端智能宠物用品需求增长"
            },
            {
              "trend": "AIoT技术普及",
              "impact": "降低智能硬件成本，提升产品可行性"
            },
            {
              "trend": "健康管理与数据化养宠",
              "impact": "催生对饮食健康监测功能的需求"
            }
          ],
          "technology_trends": [
            "边缘AI计算在终端设备的应用",
            "多模态感知技术融合",
            "宠物健康数据分析算法优化"
          ],
          "market_growth_drivers": [
            "全球宠物经济规模持续扩大",
            "智能家居生态日趋完善",
            "后疫情时代远程关注宠物需求提升"
          ],
          "potential_challenges": [
            "用户隐私与数据安全顾虑",
            "市场教育成本较高",
            "技术可靠性要求极高（涉及宠物生命安全）"
          ]
        },
        "strategic_recommendations": [
          "聚焦一二线城市高端市场，通过科技媒体与宠物KOL进行精准营销",
          "与宠物医院、保险机构合作，构建健康管理生态",
          "持续迭代AI算法，拓展行为识别、健康预警等增值功能",
          "建立严格的数据安全与隐私保护体系，增强用户信任"
        ]
      }
    },
    "supply_chain_expert": {
      "产品概述": {
        "产品名称": "AI视觉智能宠物喂食器",
        "核心功能": "AI视觉识别宠物、自动定时定量喂食、远程监控、健康数据记录、多宠物识别"
      },
      "供应链结构": {
        "上游供应商": {
          "硬件组件": [
            "主控芯片供应商（如：瑞芯微、全志科技、晶晨半导体）",
            "AI视觉模组供应商（如：海康威视、大华股份、奥比中光）",
            "电机与传动机构供应商（如：德昌电机、日本电产）",
            "塑料外壳与模具供应商（如：捷普、富士康）",
            "食品存储容器供应商（食品级塑料厂商）"
          ],
          "软件与云服务": [
            "AI算法供应商（如：商汤科技、旷视科技）",
            "云服务平台（如：阿里云、AWS、腾讯云）",
            "移动应用开发团队"
          ]
        },
        "中游制造": {
          "组装代工厂": "通常为消费电子代工厂（如：富士康、比亚迪电子、立讯精密）",
          "质量控制": "厂内QA/QC团队、第三方检测机构（如：SGS、BV）"
        },
        "下游渠道": {
          "线上渠道": "品牌官网、亚马逊、天猫、京东",
          "线下渠道": "宠物用品专卖店、大型商超、宠物医院",
          "国际市场": "通过本地分销商或跨境电商平台进入欧美、日韩市场"
        }
      },
      "关键供应商分析": {
        "战略级供应商": [
          {
            "类别": "AI视觉模组",
            "关键性": "核心差异化组件，直接影响产品识别精度与用户体验",
            "潜在供应商": "海康威视、大华股份"
          },
          {
            "类别": "主控芯片",
            "关键性": "设备计算与控制中枢，影响系统稳定性与功耗",
            "潜在供应商": "瑞芯微、全志科技"
          }
        ],
        "瓶颈供应商": [
          {
            "类别": "定制化传动机构",
            "关键性": "非标件，切换供应商需重新验证，可能影响出货周期",
            "潜在供应商": "中小型精密机械加工厂"
          }
        ]
      },
      "物流路径": {
        "原材料物流": "供应商 → 代工厂（陆运/空运，中国长三角/珠三角内部流转为主）",
        "生产物流": "代工厂内部流转（生产线→仓库）",
        "成品物流": {
          "国内销售": "代工厂仓库 → 区域配送中心（RDC） → 消费者（快递物流）",
          "国际销售": "代工厂 → 出口港（深圳/上海） → 目的国港口 → 海外仓 → 本地配送"
        },
        "退货逆向物流": "消费者 → 售后服务中心 → 检测/维修/报废处理"
      },
      "风险点分析": {
        "供应风险": [
          {
            "风险类型": "芯片短缺",
            "描述": "全球芯片供应波动可能影响主控芯片交付",
            "缓解措施": "与多家芯片供应商合作，建立安全库存"
          },
          {
            "风险类型": "单一源供应商依赖",
            "描述": "AI算法或特定硬件依赖单一供应商",
            "缓解措施": "技术模块化设计，评估备用供应商"
          }
        ],
        "生产风险": [
          {
            "风险类型": "质量一致性",
            "描述": "不同批次产品可能存在性能差异",
            "缓解措施": "严格出厂检验，建立质量追溯系统"
          }
        ],
        "物流风险": [
          {
            "风险类型": "国际运输延误",
            "描述": "海运/空运运力紧张、港口拥堵",
            "缓解措施": "多运输方案备选，提前规划发货周期"
          },
          {
            "风险类型": "跨境合规",
            "描述": "不同国家电器安全、无线电认证要求差异",
            "缓解措施": "提前获取目标市场认证（如CE、FCC）"
          }
        ],
        "技术风险": [
          {
            "风险类型": "数据安全与隐私",
            "描述": "AI视觉数据采集可能引发用户隐私担忧",
            "缓解措施": "本地化数据处理、明确隐私政策、符合GDPR等法规"
          },
          {
            "风险类型": "算法误识别",
            "描述": "多宠物场景下识别错误导致喂食不准",
            "缓解措施": "持续优化算法、提供手动校准功能"
          }
        ],
        "市场风险": [
          {
            "风险类型": "季节性需求波动",
            "描述": "节假日前后可能出现订单高峰",
            "缓解措施": "基于历史数据预测，与代工厂签订弹性产能协议"
          }
        ]
      },
      "建议优化方向": [
        "与关键供应商建立战略合作，确保供应稳定性与技术支持",
        "在主要销售区域设立前置仓，缩短交付时间",
        "建立供应链数字化平台，实现从原材料到交付的全流程可视化管理",
        "定期进行供应链压力测试，评估地缘政治、自然灾害等潜在中断风险"
      ]
    },
    "manufacturing_engineer": {
      "project_name": "AI视觉智能宠物喂食器生产工艺分析报告",
      "analysis_date": "2023-10-15",
      "product_overview": "集成AI视觉识别、自动投食、远程控制、健康监测功能的智能宠物喂食设备",
      "manufacturing_analysis": {
        "key_components": [
          {
            "name": "主控单元",
            "description": "含AI处理芯片（如RK3588或专用AIoT芯片）、内存模块",
            "manufacturing_process": "SMT贴片 → 回流焊 → 功能测试 → 三防漆涂覆"
          },
          {
            "name": "视觉模块",
            "description": "200万像素广角摄像头+红外补光模块",
            "manufacturing_process": "镜头组装 → 传感器贴合 → 焦距校准 → 成像测试"
          },
          {
            "name": "机械结构",
            "description": "食品级ABS料仓+不锈钢出料机构+步进电机",
            "manufacturing_process": "注塑成型（料仓） → CNC加工（金属件） → 超声波焊接 → 气密性测试"
          },
          {
            "name": "供电系统",
            "description": "12V/2A电源适配器+备用锂电池模块",
            "manufacturing_process": "PCB组装 → 老化测试 → 安规认证（UL/CE）"
          }
        ],
        "assembly_flow": [
          "SMT产线完成主板贴片",
          "模块预测试（摄像头、电机、传感器）",
          "结构件装配（料仓+传动机构）",
          "电气总装（主板+电源+连接线）",
          "固件烧录与AI模型部署",
          "整机老化测试（48小时连续运行）",
          "最终包装（含干燥剂、配件）"
        ],
        "critical_processes": [
          {
            "process": "AI视觉标定",
            "control_point": "使用标准色卡与测试图案校准色彩还原与识别精度",
            "tolerance": "识别准确率≥98%（测试数据集）"
          },
          {
            "process": "出料精度控制",
            "control_point": "每5g投食量误差检测",
            "tolerance": "单次误差≤±0.5g，累计误差≤±1g/100g"
          },
          {
            "process": "密封性测试",
            "control_point": "负压检测（-5kPa保持30秒）",
            "tolerance": "压力衰减≤0.1kPa"
          }
        ]
      },
      "quality_control_system": {
        "incoming_inspection": [
          "芯片上机验证（抽样率：AQL 0.65%）",
          "结构件尺寸抽检（关键尺寸100%检测）",
          "食品级材料合规证书核查"
        ],
        "in_process_control": [
          "AOI自动光学检测（主板焊点）",
          "功能测试工站（每个装配环节后）",
          "气密性在线监测（装配完成后）"
        ],
        "final_testing": [
          "AI识别率测试（使用20种标准测试物品）",
          "投食精度测试（10次连续投食循环）",
          "网络连接稳定性测试（72小时压力测试）",
          "跌落测试（抽样进行76cm六面跌落）"
        ],
        "reliability_standards": [
          "MTBF≥30000小时",
          "工作温度：0-40℃",
          "湿度耐受：10%-90% RH（非凝结）"
        ]
      },
      "cost_breakdown": {
        "material_cost": {
          "electronics": 45.2,
          "mechanical_parts": 28.7,
          "packaging": 5.3,
          "total_material": 79.2
        },
        "manufacturing_cost": {
          "pcb_assembly": 8.5,
          "product_assembly": 6.2,
          "testing": 4.8,
          "total_manufacturing": 19.5
        },
        "overhead_cost": {
          "tooling_amortization": 3,
          "quality_assurance": 2.5,
          "factory_overhead": 4,
          "total_overhead": 9.5
        },
        "cost_summary": {
          "total_unit_cost": 108.2,
          "cost_optimization_notes": [
            "建议采用JIT模式降低电子料库存成本",
            "结构件模具优化可降低15%注塑成本",
            "测试自动化率提升至80%可降低人工检测成本"
          ]
        }
      },
      "production_recommendations": [
        "建立AI模型OTA升级的产线烧录流程",
        "增加防呆设计防止电机装配错误",
        "实施MES系统追溯每个产品的测试数据",
        "关键供应商实施VMI（供应商管理库存）模式"
      ]
    },
    "materials_scientist": {
      "产品名称": "AI视觉智能宠物喂食器",
      "材料分析报告": {
        "主要部件材料选择": {
          "外壳": {
            "常用材料": "ABS塑料或食品级PP塑料",
            "材料特性": [
              "高强度、耐冲击",
              "易成型、成本适中",
              "食品接触安全性（PP更优）",
              "表面易清洁"
            ],
            "替代方案": [
              "可降解生物塑料（如PLA）",
              "再生塑料（PCR）",
              "金属外壳（不锈钢，成本较高）"
            ]
          },
          "储粮仓": {
            "常用材料": "食品级PP或AS塑料",
            "材料特性": [
              "高透明度（AS更优）",
              "防潮防氧化",
              "无毒无味",
              "耐磨损"
            ],
            "替代方案": [
              "食品级硅胶密封圈增强密封性",
              "不锈钢内胆（防腐蚀，成本高）"
            ]
          },
          "出粮机构": {
            "常用材料": "食品级POM或尼龙（齿轮/螺旋）",
            "材料特性": [
              "低摩擦系数、耐磨",
              "高尺寸稳定性",
              "耐疲劳性",
              "耐潮湿"
            ],
            "替代方案": [
              "不锈钢机械部件（耐久性更佳）",
              "陶瓷涂层部件（防粘附）"
            ]
          },
          "电子部件封装": {
            "常用材料": "阻燃PC/ABS合金",
            "材料特性": [
              "阻燃等级（UL94 V-0）",
              "电磁屏蔽性能",
              "散热设计兼容性"
            ],
            "替代方案": [
              "导热塑料（提升散热效率）",
              "金属屏蔽罩局部增强"
            ]
          }
        },
        "关键材料特性要求": [
          "食品安全性（符合FDA/GB标准）",
          "耐候性（适应厨房潮湿环境）",
          "抗菌性能（减少霉菌滋生）",
          "结构稳定性（长期使用不变形）",
          "轻量化与成本平衡"
        ],
        "环保性评估": {
          "积极方面": [
            "可优先选用食品级再生塑料",
            "模块化设计便于部件更换而非整机废弃",
            "低功耗电子元件减少能源消耗"
          ],
          "改进建议": [
            "采用可追溯的环保材料认证（如TÜV、EPEAT）",
            "提供官方回收渠道或材料标识（如塑料回收编码）",
            "优化包装材料（使用可降解或再生纸板）",
            "延长设计寿命（通过耐老化材料选择）"
          ],
          "潜在挑战": [
            "电子元件回收需专业处理",
            "混合材料结构可能增加拆解难度"
          ]
        },
        "创新材料建议": [
          "添加抗菌母粒（银离子或锌离子）的塑料",
          "使用竹纤维复合塑料（部分替代石油基材料）",
          "可拆卸硅胶密封件（便于清洁和更换）",
          "光降解添加剂（用于户外版本外壳）"
        ]
      },
      "总结": "当前智能宠物喂食器材料选择以食品级工程塑料为主，在安全性、成本和加工性间取得平衡。未来可通过生物基材料、模块化设计和回收体系优化，显著提升产品的全生命周期环保性能。"
    },
    "cost_analyst": {
      "产品名称": "AI视觉智能宠物喂食器",
      "成本结构分析": {
        "直接材料成本": [
          {
            "组件": "主控芯片与AI视觉模块",
            "占比": "约25%",
            "说明": "包括AI处理器、摄像头、传感器等核心部件，通常采用中端SoC方案"
          },
          {
            "组件": "机械结构与储粮仓",
            "占比": "约20%",
            "说明": "食品级塑料/不锈钢主体、出粮电机、密封结构"
          },
          {
            "组件": "电源与通信模块",
            "占比": "约15%",
            "说明": "电源适配器、Wi-Fi/蓝牙模块、备用电池"
          },
          {
            "组件": "包装与配件",
            "占比": "约10%",
            "说明": "环保包装、说明书、电源线、粮勺等"
          }
        ],
        "直接制造成本": [
          {
            "项目": "组装与测试",
            "占比": "约8%",
            "说明": "生产线组装、AI算法烧录、功能测试"
          },
          {
            "项目": "生产损耗",
            "占比": "约2%",
            "说明": "物料损耗率控制在3%以内"
          }
        ],
        "间接成本": [
          {
            "项目": "研发摊销",
            "占比": "约10%",
            "说明": "AI视觉算法开发、App开发、工业设计等前期投入分摊"
          },
          {
            "项目": "运营与物流",
            "占比": "约5%",
            "说明": "仓储、运输、关税（如涉及出口）"
          },
          {
            "项目": "管理与销售费用",
            "占比": "约5%",
            "说明": "团队管理、市场推广、渠道费用"
          }
        ],
        "成本总计": "直接材料成本约70%，直接制造成本约10%，间接成本约20%",
        "备注": "以上为预估比例，实际成本随采购规模、技术方案、生产地区等因素浮动"
      },
      "定价策略分析": {
        "市场定位": "中高端智能宠物用品",
        "定价方法": "价值导向定价 + 竞争参考定价",
        "建议零售价范围": "人民币800-1500元",
        "定价依据": [
          {
            "因素": "竞品对标",
            "说明": "基础喂食器价格在300-600元，AI视觉功能溢价明显"
          },
          {
            "因素": "目标用户支付意愿",
            "说明": "宠物主对健康监控、互动功能有较高支付意愿"
          },
          {
            "因素": "渠道分层定价",
            "说明": "线上直营价较低，线下宠物店/宠物医院渠道加价率30-50%"
          }
        ]
      },
      "利润空间分析": {
        "成本占比假设": "以建议零售价中位数1200元为基准",
        "制造成本": "约480元（占40%）",
        "毛利率": "约60%（720元）",
        "净利率预估": "约20-30%（扣除研发、营销、售后等费用后）",
        "关键利润驱动因素": [
          "AI算法软件化带来的高附加值",
          "后续服务收入（如云端存储、高级识别功能订阅）",
          "耗材与配件销售（专用粮盒、清洁套件）"
        ]
      },
      "成本优化建议": [
        {
          "领域": "供应链优化",
          "建议": "与芯片供应商签订长期采购协议，考虑采用国产AI芯片替代方案以降低核心部件成本10-15%"
        },
        {
          "领域": "设计优化",
          "建议": "模块化设计，简化装配步骤，降低组装成本5-8%"
        },
        {
          "领域": "生产优化",
          "建议": "在销量提升后转移至自动化程度更高的产线，降低单位人工成本"
        },
        {
          "领域": "间接成本控制",
          "建议": "采用云端AI服务分摊研发成本，通过合作伙伴渠道降低营销费用占比"
        },
        {
          "领域": "长期策略",
          "建议": "开发简配版（无视觉功能）覆盖低端市场，形成产品矩阵；通过用户数据积累优化算法，降低后续版本研发边际成本"
        }
      ],
      "风险提示": [
        "核心芯片供应波动可能影响成本稳定性",
        "AI算法持续优化需要长期研发投入",
        "宠物智能用品市场竞争加剧可能导致价格下行压力"
      ]
    },
    "sustainability_expert": {
      "产品名称": "AI视觉智能宠物喂食器",
      "分析维度": {
        "环境影响": {
          "正面影响": [
            "精准投喂减少宠物食物浪费，降低宠物食品生产链的间接资源消耗",
            "远程监控减少用户出行需求，可能降低交通碳排放",
            "健康监测功能可预防宠物疾病，减少医疗资源消耗"
          ],
          "负面影响": [
            "电子元件生产涉及稀土金属开采和化工污染",
            "塑料外壳可能使用石油基材料",
            "数据中心运行耗能（AI图像处理）",
            "产品寿命周期较短（约3-5年）产生电子垃圾"
          ]
        },
        "碳足迹评估": {
          "阶段分布": {
            "原材料阶段": "约占总碳足迹的45%（含芯片、传感器、塑料壳体）",
            "生产制造": "约25%（精密组装耗能）",
            "运输阶段": "约10%（全球供应链运输）",
            "使用阶段": "约15%（电力消耗+云端数据处理）",
            "废弃阶段": "约5%（回收处理能耗）"
          },
          "估算总量": "约18-22kg CO2e/台（假设5年使用周期）"
        },
        "循环经济潜力": {
          "设计改进潜力": [
            "模块化设计便于维修和部件更换",
            "采用生物基塑料或再生塑料",
            "标准化接口支持功能升级而非整体更换"
          ],
          "商业模式创新": [
            "提供设备租赁+健康管理订阅服务",
            "建立旧设备回收翻新体系",
            "与宠物食品企业合作实现包装物回收闭环"
          ],
          "材料回收可行性": {
            "高价值材料": "PCB板金属回收率可达85%",
            "中价值材料": "电机和传感器可再制造",
            "低价值材料": "混合塑料需化学回收"
          }
        },
        "绿色改进方案": [
          {
            "类别": "材料创新",
            "具体措施": [
              "使用30%以上再生塑料或聚乳酸（PLA）生物塑料",
              "采用无卤素阻燃电路板",
              "包装改用蘑菇菌丝体或再生纸浆材料"
            ],
            "预期减排效果": "降低原材料阶段碳足迹15-20%"
          },
          {
            "类别": "能效优化",
            "具体措施": [
              "增加太阳能辅助供电模块",
              "采用低功耗边缘计算芯片减少云端数据传输",
              "设置智能休眠模式（非用餐时段待机功耗<0.5W）"
            ],
            "预期减排效果": "降低使用阶段能耗40%"
          },
          {
            "类别": "生命周期延伸",
            "具体措施": [
              "提供官方维修服务和备件市场",
              "设计软件升级延长功能生命周期",
              "建立以旧换新制度确保旧设备规范回收"
            ],
            "预期效果": "将平均使用寿命延长至7年以上"
          },
          {
            "类别": "系统协同",
            "具体措施": [
              "与智能电网联动在用电低谷期运行",
              "集成宠物食品余量监测自动触发环保包装配送",
              "用户社区共享设备闲置时段喂食能力（宠物托管）"
            ],
            "系统性效益": "构建宠物护理绿色生态系统"
          }
        ]
      },
      "综合建议": "建议企业开展产品生命周期评估（LCA）认证，优先实施模块化设计和再生材料应用，探索设备即服务（DaaS）商业模式，并与可再生能源供应商合作推出绿色宠物护理套餐。"
    },
    "innovation_strategist": {
      "analysis_report": {
        "product_name": "AI视觉智能宠物喂食器",
        "analysis_date": "2024-07-20",
        "sections": {
          "technological_innovations": {
            "description": "当前AI视觉智能宠物喂食器的核心技术突破点",
            "points": [
              {
                "id": "TI-01",
                "name": "多模态感知融合",
                "description": "结合视觉传感器、重量传感器、声音采集设备，实现宠物身份识别、进食行为分析和健康状态监测"
              },
              {
                "id": "TI-02",
                "name": "边缘AI计算",
                "description": "设备端部署轻量化神经网络模型，实现实时宠物识别（品种、个体）、进食姿态分析和异常行为检测"
              },
              {
                "id": "TI-03",
                "name": "个性化营养算法",
                "description": "基于宠物品种、年龄、体重、活动量及健康数据，动态调整喂食计划和营养配比"
              },
              {
                "id": "TI-04",
                "name": "人机交互创新",
                "description": "支持语音指令、移动端远程监控、进食数据可视化及智能提醒功能"
              },
              {
                "id": "TI-05",
                "name": "智能存储系统",
                "description": "集成温湿度控制、密封保鲜、存量监测和自动补给提醒的智能粮仓系统"
              }
            ]
          },
          "future_development_directions": {
            "description": "未来3-5年的技术演进和市场拓展方向",
            "directions": [
              {
                "category": "技术深化",
                "items": [
                  "生物特征识别升级（虹膜/鼻纹识别精度提升至99.9%）",
                  "健康预测算法（通过进食行为早期发现疾病征兆）",
                  "多宠物家庭场景优化（同时识别管理多只宠物）"
                ]
              },
              {
                "category": "生态扩展",
                "items": [
                  "与宠物医院数据系统对接",
                  "宠物保险服务联动",
                  "智能宠物家居生态系统集成"
                ]
              },
              {
                "category": "服务模式创新",
                "items": [
                  "订阅制营养方案服务",
                  "远程兽医咨询接口",
                  "宠物社交数据共享（匿名化）"
                ]
              }
            ]
          },
          "disruptive_opportunities": {
            "description": "可能颠覆传统宠物护理行业的潜在机会",
            "opportunities": [
              {
                "id": "DO-01",
                "name": "预防性宠物医疗革命",
                "description": "通过日常进食数据建立健康基线，提前3-6个月预警潜在健康问题，改变被动治疗模式",
                "potential_impact": "可能减少30%的突发性宠物医疗支出"
              },
              {
                "id": "DO-02",
                "name": "宠物营养个性化定制",
                "description": "基于实时数据自动调整或推荐定制粮配方，推动宠物食品行业从批量生产转向个性化制造",
                "potential_impact": "创造千亿级个性化宠物食品市场"
              },
              {
                "id": "DO-03",
                "name": "宠物行为数字孪生",
                "description": "建立宠物行为数字模型，为训练、寄养、保险等场景提供量化评估依据",
                "potential_impact": "重构宠物服务行业标准体系"
              },
              {
                "id": "DO-04",
                "name": "跨物种智能关怀平台",
                "description": "技术框架可扩展至其他宠物类型（爬宠、鸟类等），形成统一智能宠物管理平台",
                "potential_impact": "扩大市场覆盖至全宠物品类"
              }
            ]
          },
          "innovation_recommendations": {
            "description": "战略创新实施建议",
            "recommendations": [
              {
                "priority": "高",
                "area": "技术研发",
                "suggestions": [
                  "开发开源AI模型框架，吸引开发者生态",
                  "与芯片厂商合作研发专用边缘AI处理器",
                  "建立宠物行为开源数据集，推动行业标准"
                ]
              },
              {
                "priority": "高",
                "area": "商业模式",
                "suggestions": [
                  "采用\"设备+订阅服务\"双收入模式",
                  "与宠物保险公司推出数据增值服务",
                  "建立B2B2C渠道，与宠物医院、美容店合作"
                ]
              },
              {
                "priority": "中",
                "area": "用户体验",
                "suggestions": [
                  "开发AR远程互动喂食功能",
                  "增加环境感知模块（温湿度、空气质量）",
                  "设计模块化硬件，支持功能扩展"
                ]
              },
              {
                "priority": "中",
                "area": "数据安全",
                "suggestions": [
                  "实施端到端加密数据传输",
                  "获得宠物数据隐私安全认证",
                  "提供本地化数据存储选项"
                ]
              }
            ]
          }
        },
        "strategic_insights": {
          "key_conclusion": "AI视觉智能宠物喂食器正从单一喂食工具向宠物健康管理平台演进，其核心价值将从设备销售转向数据服务。建议优先构建宠物健康数据生态系统，并与宠物医疗、保险、食品行业形成战略联盟。",
          "timeline_recommendation": {
            "short_term": "12个月内聚焦多宠物识别精度提升和基础健康监测功能",
            "medium_term": "24个月内建立行业数据标准并拓展2-3个关键合作伙伴",
            "long_term": "36-48个月构建完整的宠物健康预防管理服务平台"
          }
        }
      }
    }
  },
  "productionAnalysis": {},
  "priority": 0,
  "isActive": true
}